clck/__init__.py
clck/clck.py
clck.ru-1.0.0.dist-info/LICENSE
clck.ru-1.0.0.dist-info/METADATA
clck.ru-1.0.0.dist-info/WHEEL
clck.ru-1.0.0.dist-info/top_level.txt
clck.ru-1.0.0.dist-info/RECORD
